jira/__init__.py
jira/client.py
jira/config.py
jira/exceptions.py
jira/jirashell.py
jira/py.typed
jira/resilientsession.py
jira/resources.py
jira/utils/LICENSE
jira/utils/__init__.py
jira-3.10.4.dist-info/licenses/AUTHORS.rst
jira-3.10.4.dist-info/licenses/LICENSE
jira-3.10.4.dist-info/METADATA
jira-3.10.4.dist-info/WHEEL
jira-3.10.4.dist-info/entry_points.txt
jira-3.10.4.dist-info/top_level.txt
jira-3.10.4.dist-info/RECORD
