Metadata-Version: 2.4
Name: jira
Version: 3.10.4
Summary: Python library for interacting with JIRA via REST APIs.
Author-email: Ben Speakmon <ben.speakmon@gmail.com>
Maintainer-email: Sorin Sbarnea <sorin.sbarnea@gmail.com>
Project-URL: Bug Tracker, https://github.com/pycontribs/jira/issues
Project-URL: CI: GitHub Actions, https://github.com/pycontribs/jira/actions
Project-URL: Documentation, https://jira.readthedocs.io
Project-URL: Forum, https://community.atlassian.com/t5/tag/jira-python/tg-p?sort=recent
Project-URL: Homepage, https://github.com/pycontribs/jira
Project-URL: Release Management, https://github.com/pycontribs/jira/projects
Project-URL: Source Code, https://github.com/pycontribs/jira.git
Keywords: api,atlassian,jira,rest,web
Platform: any
Classifier: Development Status :: 5 - Production/Stable
Classifier: Environment :: Other Environment
Classifier: Intended Audience :: Developers
Classifier: Intended Audience :: Information Technology
Classifier: License :: OSI Approved :: BSD License
Classifier: Operating System :: OS Independent
Classifier: Programming Language :: Python
Classifier: Programming Language :: Python :: 3
Classifier: Programming Language :: Python :: 3 :: Only
Classifier: Programming Language :: Python :: 3.10
Classifier: Programming Language :: Python :: 3.11
Classifier: Programming Language :: Python :: 3.12
Classifier: Topic :: Software Development :: Libraries :: Python Modules
Classifier: Topic :: Internet :: WWW/HTTP
Requires-Python: >=3.10
License-File: LICENSE
License-File: AUTHORS.rst
Requires-Dist: defusedxml
Requires-Dist: packaging
Requires-Dist: requests-oauthlib>=1.1.0
Requires-Dist: requests>=2.10.0
Requires-Dist: requests_toolbelt
Requires-Dist: typing_extensions>=3.7.4.2
Provides-Extra: async
Requires-Dist: requests-futures>=0.9.7; extra == "async"
Provides-Extra: cli
Requires-Dist: ipython>=4.0.0; extra == "cli"
Requires-Dist: keyring; extra == "cli"
Provides-Extra: docs
Requires-Dist: sphinx>=5.0.0; extra == "docs"
Requires-Dist: sphinx-copybutton; extra == "docs"
Requires-Dist: furo; extra == "docs"
Provides-Extra: opt
Requires-Dist: filemagic>=1.6; extra == "opt"
Requires-Dist: PyJWT; extra == "opt"
Requires-Dist: requests_jwt; extra == "opt"
Requires-Dist: requests_kerberos; extra == "opt"
Provides-Extra: test
Requires-Dist: MarkupSafe>=0.23; extra == "test"
Requires-Dist: PyYAML>=5.1; extra == "test"
Requires-Dist: docutils>=0.21.2; extra == "test"
Requires-Dist: flaky; extra == "test"
Requires-Dist: oauthlib; extra == "test"
Requires-Dist: parameterized>=0.8.1; extra == "test"
Requires-Dist: pip; extra == "test"
Requires-Dist: pytest-cache; extra == "test"
Requires-Dist: pytest-cov; extra == "test"
Requires-Dist: pytest-instafail; extra == "test"
Requires-Dist: pytest-sugar; extra == "test"
Requires-Dist: pytest-timeout>=1.3.1; extra == "test"
Requires-Dist: pytest-xdist>=2.2; extra == "test"
Requires-Dist: pytest>=6.0.0; extra == "test"
Requires-Dist: requests_mock; extra == "test"
Requires-Dist: requires.io; extra == "test"
Requires-Dist: tenacity; extra == "test"
Requires-Dist: wheel>=0.24.0; extra == "test"
Requires-Dist: yanc>=0.3.3; extra == "test"
Requires-Dist: parameterized>=0.8.1; extra == "test"
Dynamic: license-file
